python_xonotic_db-0.3.0.dist-info/DESCRIPTION.rst
python_xonotic_db-0.3.0.dist-info/METADATA
python_xonotic_db-0.3.0.dist-info/RECORD
python_xonotic_db-0.3.0.dist-info/WHEEL
python_xonotic_db-0.3.0.dist-info/entry_points.txt
python_xonotic_db-0.3.0.dist-info/metadata.json
python_xonotic_db-0.3.0.dist-info/top_level.txt
tests/__init__.py
tests/conftest.py
tests/test_cli.py
tests/test_crc.py
tests/test_main.py
tests/test_natural_sort.py
xon_db/__init__.py
xon_db/cli.py
xon_db/crc.py
xon_db/natural_sort.py
